bqbraket/__init__.py
bqbraket/_version.py
bqbraket/backend.py
braket_backend_blueqat-0.0.5.dist-info/LICENSE
braket_backend_blueqat-0.0.5.dist-info/METADATA
braket_backend_blueqat-0.0.5.dist-info/WHEEL
braket_backend_blueqat-0.0.5.dist-info/top_level.txt
braket_backend_blueqat-0.0.5.dist-info/RECORD
