Metadata-Version: 2.1
Name: braket-backend-blueqat
Version: 0.0.5
Summary: Braket backend for blueqat
Author: gyu-don
Author-email: kato@blueqat.com
License: Apache-2.0
Platform: UNKNOWN
Classifier: Development Status :: 3 - Alpha
Classifier: License :: OSI Approved :: Apache Software License
Classifier: Programming Language :: Python :: 3.7
Classifier: Programming Language :: Python :: 3.8
Classifier: Programming Language :: Python :: 3.9
License-File: LICENSE
Requires-Dist: blueqat (>=0.4.9)
Requires-Dist: amazon-braket-sdk (>=1.5.13)
